voica/__init__.py
voica-0.1.3.dist-info/METADATA
voica-0.1.3.dist-info/WHEEL
voica-0.1.3.dist-info/top_level.txt
voica-0.1.3.dist-info/RECORD
