Metadata-Version: 2.1
Name: voica
Version: 0.1.3
Author: voica
Author-email: nmaks6385@gmail.com
Classifier: Programming Language :: Python :: 3
Classifier: License :: OSI Approved :: MIT License
Classifier: Operating System :: OS Independent
Requires-Python: >=3.6
